{
  "reviews": [
    {
      "id": 1,
      "product_id": 15428343497086,
      "product_title": "Apple Pie Cookie",
      "reviewer_name": "Granny Smith",
      "email": "granny.smith@example.com",
      "rating": 5,
      "review_title": "Simply Divine!",
      "comment": "These are absolutely incredible! They truly taste like a bite of homemade apple pie. The caramelized apples are a game-changer.",
      "date": "2025-06-16",
      "likes": 24,
      "dislikes": 2
    },
    {
      "id": 2,
      "product_id": 15428343497086,
      "product_title": "Apple Pie Cookie",
      "reviewer_name": "PieLover22",
      "email": "pielover22@example.com",
      "rating": 4,
      "review_title": "Almost Perfect",
      "comment": "Delicious! Warm and chewy, perfectly spiced. Just wish they were a tiny bit larger, but still a fantastic treat.",
      "image_url": "https://picsum.photos/id/237/200/200",
      "date": "2025-06-15",
      "likes": 15,
      "dislikes": 1
    },
    {
      "id": 3,
      "product_id": 15428343497086,
      "product_title": "Apple Pie Cookie",
      "reviewer_name": "CookieMon",
      "email": "cookiemonsterx@example.com",
      "rating": 5,
      "review_title": "New Favorite!",
      "comment": "Seriously good! The balance of tangy apple and sweet vanilla is spot on. A new favorite for sure.",
      "image_url": "https://picsum.photos/seed/picsum/200/200",
      "date": "2025-06-14",
      "likes": 32,
      "dislikes": 0
    },
    {
      "id": 4,
      "product_id": 15428343497086,
      "product_title": "Apple Pie Cookie",
      "reviewer_name": "DessertDiva",
      "email": "dessertdiva@example.com",
      "rating": 5,
      "review_title": "Family Favorite",
      "comment": "My entire family loved these. Fresh, flavorful, and a true taste of Americana. Will definitely order again!",
      "image_url": "https://picsum.photos/seed/picsum/200/200",
      "date": "2025-06-13",
      "likes": 28,
      "dislikes": 0
    },
    {
      "id": 5,
      "product_id": 15428343497086,
      "product_title": "Apple Pie Cookie",
      "reviewer_name": "SweetToothGuy",
      "email": "sweetoothguy@example.com",
      "rating": 4,
      "review_title": "Great Quality",
      "comment": "Very tasty, the apple filling is generous. The cookie itself is soft and chewy. Great quality.",
      "image_url": "https://picsum.photos/seed/picsum/200/200",
      "date": "2025-06-12",
      "likes": 19,
      "dislikes": 0
    },
    {
      "id": 6,
      "product_id": 15428343497086,
      "product_title": "Apple Pie Cookie",
      "reviewer_name": "BakerBob",
      "email": "bakerbob@example.com",
      "rating": 5,
      "review_title": "Excellent Craftsmanship",
      "comment": "As a baker myself, I appreciate the craftsmanship. Organic ingredients really shine through. Perfect texture.",
      "image_url": "https://picsum.photos/seed/picsum/200/200",
      "date": "2025-06-11",
      "likes": 40,
      "dislikes": 1
    },
    {
      "id": 7,
      "product_id": 15428343497086,
      "product_title": "Apple Pie Cookie",
      "reviewer_name": "CrispyCritique",
      "email": "crispycritique@example.com",
      "rating": 3,
      "review_title": "A Bit Too Soft",
      "comment": "Good flavor, but a bit too soft for my preference. I prefer a crispier cookie. Still enjoyable though.",
      "image_url": "https://picsum.photos/seed/picsum/200/200",
      "date": "2025-06-10",
      "likes": 8,
      "dislikes": 5
    },
    {
      "id": 8,
      "product_id": 15428343497086,
      "product_title": "Apple Pie Cookie",
      "reviewer_name": "HappilyFed",
      "email": "happilyfed@example.com",
      "rating": 5,
      "review_title": "Gourmet Experience",
      "comment": "So impressed! They arrived fresh and well-packaged. The taste exceeded my expectations. A gourmet cookie experience.",
      "image_url": "https://picsum.photos/seed/picsum/200/200",
      "date": "2025-06-09",
      "likes": 35,
      "dislikes": 0
    },
    {
      "id": 9,
      "product_id": 15428343497086,
      "product_title": "Apple Pie Cookie",
      "reviewer_name": "Jonny Appleseed",
      "email": "jonny.appleseed@example.com",
      "rating": 4,
      "review_title": "Authentic Apple Flavor",
      "comment": "If you love apple pie, you'll love these. The flavors are very authentic. Great for a quick dessert.",
      "image_url": "https://picsum.photos/seed/picsum/200/200",
      "date": "2025-06-08",
      "likes": 20,
      "dislikes": 0
    },
    {
      "id": 10,
      "product_id": 15428343497086,
      "product_title": "Apple Pie Cookie",
      "reviewer_name": "EveFromEden",
      "email": "eve.eden@example.com",
      "rating": 5,
      "review_title": "Heavenly!",
      "comment": "Worth being cast out of Eden for, indeed! These cookies are heavenly. The cane sugar and vanilla balance the apple perfectly.",
      "image_url": "https://picsum.photos/seed/picsum/200/200",
      "date": "2025-06-07",
      "likes": 45,
      "dislikes": 0
    },
    {
      "id": 11,
      "product_id": 15428343497086,
      "product_title": "Apple Pie Cookie",
      "reviewer_name": "Teacher'sPet",
      "email": "teachers.pet@example.com",
      "rating": 5,
      "review_title": "Big Hit at School!",
      "comment": "Gave one to my teacher, and it was a huge hit! Everyone in the staff room wanted to know where I got them.",
      "image_url": "https://picsum.photos/seed/picsum/200/200",
      "date": "2025-06-06",
      "likes": 18,
      "dislikes": 0
    },
    {
      "id": 12,
      "product_id": 15428343497086,
      "product_title": "Apple Pie Cookie",
      "reviewer_name": "DailyDose",
      "email": "dailydose@example.com",
      "rating": 4,
      "review_title": "Satisfying Treat",
      "comment": "An apple pie cookie a day keeps the hunger away! Seriously satisfying. Would buy again.",
      "date": "2025-06-05",
      "likes": 12,
      "dislikes": 0
    },
    {
      "id": 13,
      "product_id": 15428342579582,
      "product_title": "Belgian Hazelnut Cookie",
      "reviewer_name": "NutellaFan",
      "email": "nutella.fan@example.com",
      "rating": 5,
      "review_title": "A Must-Try for Nutella Lovers!",
      "comment": "If you love Nutella, you NEED this cookie. Rich, decadent, and perfectly chewy. A limited edition must-try!",
      "image_url": "https://picsum.photos/seed/picsum/200/200",
      "date": "2025-06-16",
      "likes": 30,
      "dislikes": 0
    },
    {
      "id": 14,
      "product_id": 15428342579582,
      "product_title": "Belgian Hazelnut Cookie",
      "reviewer_name": "Hazelnut2",
      "email": "hazelnut2@example.com",
      "rating": 5,
      "review_title": "Bursting with Flavor",
      "comment": "Absolutely bursting with hazelnut flavor and the organic Nutella is a fantastic touch. So glad I tried these.",
      "image_url": "https://picsum.photos/seed/picsum/200/200",
      "date": "2025-06-15",
      "likes": 25,
      "dislikes": 0
    },
    {
      "id": 15,
      "product_id": 15428342579582,
      "product_title": "Belgian Hazelnut Cookie",
      "reviewer_name": "EuropeanEater",
      "email": "european.eater@example.com",
      "rating": 4,
      "review_title": "Authentic Taste",
      "comment": "A very authentic Belgian taste. Rich and satisfying. A great treat for a limited time.",
      "image_url": "https://picsum.photos/seed/picsum/200/200",
      "date": "2025-06-14",
      "likes": 18,
      "dislikes": 1
    },
    {
      "id": 16,
      "product_id": 15428342579582,
      "product_title": "Belgian Hazelnut Cookie",
      "reviewer_name": "CookieC3",
      "email": "cookie.c3@example.com",
      "rating": 5,
      "review_title": "Best Hazelnut Cookie!",
      "comment": "One of the best hazelnut cookies I've ever had. The texture is perfect and the filling is generous.",
      "image_url": "https://picsum.photos/seed/picsum/200/200",
      "date": "2025-06-13",
      "likes": 35,
      "dislikes": 0
    },
    {
      "id": 17,
      "product_id": 15428342579582,
      "product_title": "Belgian Hazelnut Cookie",
      "reviewer_name": "SweetTreat",
      "email": "sweet.treat@example.com",
      "rating": 4,
      "review_title": "Unique and Tasty",
      "comment": "Very unique and tasty! The hazelnuts add a great crunch. Definitely worth trying before it's gone.",
      "image_url": "https://picsum.photos/seed/picsum/200/200",
      "date": "2025-06-12",
      "likes": 22,
      "dislikes": 0
    },
    {
      "id": 18,
      "product_id": 15428341891454,
      "product_title": "Better than Oreo cookie",
      "reviewer_name": "OreoKiller",
      "email": "oreokiller@example.com",
      "rating": 5,
      "review_title": "They Weren't Lying!",
      "comment": "They weren't lying! This cookie is seriously better than an Oreo. Richer, more complex, and perfectly moist. I'm hooked!",
      "image_url": "https://picsum.photos/seed/picsum/200/200",
      "date": "2025-06-16",
      "likes": 50,
      "dislikes": 2
    },
    {
      "id": 19,
      "product_id": 15428341891454,
      "product_title": "Better than Oreo cookie",
      "reviewer_name": "CookieCritic",
      "email": "cookie.critic@example.com",
      "rating": 4,
      "review_title": "Strong Contender",
      "comment": "A very good chocolate cookie with a nice cream filling. It's a strong contender against the original, almost better.",
      "image_url": "https://picsum.photos/seed/picsum/200/200",
      "date": "2025-06-15",
      "likes": 38,
      "dislikes": 1
    },
    {
      "id": 20,
      "product_id": 15428341891454,
      "product_title": "Better than Oreo cookie",
      "reviewer_name": "ChocolateLover",
      "email": "chocolatelover@example.com",
      "rating": 5,
      "review_title": "Unbelievably Good!",
      "comment": "The chocolate flavor is intense and the cream filling is divine. This is my new go-to chocolate cookie. Highly recommend!",
      "image_url": "https://picsum.photos/seed/picsum/200/200",
      "date": "2025-06-14",
      "likes": 45,
      "dislikes": 0
    }
  ]
}